occult/occult.py
vpype_occult-0.4.0.dist-info/LICENSE
vpype_occult-0.4.0.dist-info/METADATA
vpype_occult-0.4.0.dist-info/WHEEL
vpype_occult-0.4.0.dist-info/entry_points.txt
vpype_occult-0.4.0.dist-info/top_level.txt
vpype_occult-0.4.0.dist-info/RECORD
