Metadata-Version: 2.1
Name: vpype-occult
Version: 0.4.0
Summary: Occlusion plug-in for vpype
Home-page: https://github.com/LoicGoulefert/occult
Author: Loic Goulefert
License: MIT License
Classifier: Development Status :: 4 - Beta
Classifier: License :: OSI Approved :: MIT License
Classifier: Topic :: Multimedia :: Graphics
Classifier: Environment :: Plugins
License-File: LICENSE
Requires-Dist: click
Requires-Dist: numpy
Requires-Dist: shapely (>=2.0.0)
Requires-Dist: vpype (<2.0,>=1.9)
